slider2d/__init__.py
slider2d/_frontend.py
slider2d/_version.py
slider2d/slider2d.py
slider2d/labextension/build_log.json
slider2d/labextension/package.json
slider2d/labextension/static/lib_index_js.7053204ac782f7271056.js
slider2d/labextension/static/lib_index_js.7053204ac782f7271056.js.map
slider2d/labextension/static/lib_plugin_js.b62f9ae4ecf95a1818bd.js
slider2d/labextension/static/lib_plugin_js.b62f9ae4ecf95a1818bd.js.map
slider2d/labextension/static/lib_widget_js.038224994ddeb3f02012.js
slider2d/labextension/static/lib_widget_js.038224994ddeb3f02012.js.map
slider2d/labextension/static/remoteEntry.937afd275c64390999d4.js
slider2d/labextension/static/remoteEntry.937afd275c64390999d4.js.map
slider2d/labextension/static/style.js
slider2d/nbextension/extension.js
slider2d/nbextension/index.js
slider2d/nbextension/index.js.LICENSE.txt
slider2d/nbextension/index.js.map
slider2d/tests/__init__.py
slider2d/tests/conftest.py
slider2d/tests/test_example.py
slider2d/tests/test_nbextension_path.py
slider2d-0.1.0.data/data/etc/jupyter/nbconfig/notebook.d/slider2d.json
slider2d-0.1.0.data/data/share/jupyter/labextensions/slider2d/build_log.json
slider2d-0.1.0.data/data/share/jupyter/labextensions/slider2d/install.json
slider2d-0.1.0.data/data/share/jupyter/labextensions/slider2d/package.json
slider2d-0.1.0.data/data/share/jupyter/labextensions/slider2d/static/lib_index_js.7053204ac782f7271056.js
slider2d-0.1.0.data/data/share/jupyter/labextensions/slider2d/static/lib_index_js.7053204ac782f7271056.js.map
slider2d-0.1.0.data/data/share/jupyter/labextensions/slider2d/static/lib_plugin_js.b62f9ae4ecf95a1818bd.js
slider2d-0.1.0.data/data/share/jupyter/labextensions/slider2d/static/lib_plugin_js.b62f9ae4ecf95a1818bd.js.map
slider2d-0.1.0.data/data/share/jupyter/labextensions/slider2d/static/lib_widget_js.038224994ddeb3f02012.js
slider2d-0.1.0.data/data/share/jupyter/labextensions/slider2d/static/lib_widget_js.038224994ddeb3f02012.js.map
slider2d-0.1.0.dist-info/LICENSE.txt
slider2d-0.1.0.dist-info/METADATA
slider2d-0.1.0.dist-info/WHEEL
slider2d-0.1.0.dist-info/top_level.txt
slider2d-0.1.0.dist-info/RECORD
